semanticlayertools/__init__.py
semanticlayertools/cleaning/__init__.py
semanticlayertools/cleaning/text.py
semanticlayertools/clustering/__init__.py
semanticlayertools/clustering/infomap.py
semanticlayertools/clustering/leiden.py
semanticlayertools/clustering/reports.py
semanticlayertools/linkage/__init__.py
semanticlayertools/linkage/citation.py
semanticlayertools/linkage/densities.py
semanticlayertools/linkage/worddistributions.py
semanticlayertools/linkage/wordscore.py
semanticlayertools/metric/__init__.py
semanticlayertools/metric/centralities.py
semanticlayertools/metric/linguistic.py
semanticlayertools/metric/prune.py
semanticlayertools/pipelines/__init__.py
semanticlayertools/pipelines/cocitetimeclusters.py
semanticlayertools/pipelines/wordscorenet.py
semanticlayertools/visual/__init__.py
semanticlayertools/visual/embedding.py
semanticlayertools/visual/plotting.py
semanticlayertools/visual/utils.py
semanticlayertools-1.1.1.dist-info/METADATA
semanticlayertools-1.1.1.dist-info/WHEEL
semanticlayertools-1.1.1.dist-info/licenses/AUTHORS.md
semanticlayertools-1.1.1.dist-info/licenses/LICENSE.md
semanticlayertools-1.1.1.dist-info/RECORD
