Metadata-Version: 2.4
Name: semanticlayertools
Version: 1.1.1
Summary: Create social, material or semantic layers using different methods to work with the Socio-epistemic networks framework.
Project-URL: Project Homepage, https://modelsen.gea.mpg.de
Project-URL: Homepage, https://gitlab.gwdg.de/modelsen/semanticlayertools
Project-URL: Issues, https://gitlab.gwdg.de/modelsen/semanticlayertools/-/issues
Author-email: Malte Vogl <vogl@gea.mpg.de>, Raphael Schlattmann <raphael.schlattmann@tu-berlin.de>
License-File: AUTHORS.md
License-File: LICENSE.md
Classifier: License :: OSI Approved :: MIT License
Classifier: Operating System :: OS Independent
Classifier: Programming Language :: Python :: 3
Requires-Python: >=3.8
Requires-Dist: bertopic
Requires-Dist: dask[dataframe]
Requires-Dist: datashader
Requires-Dist: igraph
Requires-Dist: infomap>=2.3
Requires-Dist: leidenalg
Requires-Dist: matplotlib
Requires-Dist: numpy
Requires-Dist: pandas
Requires-Dist: plotly
Requires-Dist: polars
Requires-Dist: python-dotenv
Requires-Dist: scikit-image
Requires-Dist: scikit-learn
Requires-Dist: scipy
Requires-Dist: spacy
Requires-Dist: tqdm
Provides-Extra: dev
Requires-Dist: ruff; extra == 'dev'
Requires-Dist: sphinx; extra == 'dev'
Requires-Dist: tox; extra == 'dev'
Requires-Dist: twine; extra == 'dev'
Provides-Extra: ml
Requires-Dist: accelerate; extra == 'ml'
Requires-Dist: datamapplot; extra == 'ml'
Requires-Dist: hdbscan; extra == 'ml'
Requires-Dist: plotly; extra == 'ml'
Requires-Dist: sentence-transformers; extra == 'ml'
Requires-Dist: tbb; extra == 'ml'
